archiverr-0.0.12.data/scripts/archiver
src/Archive.py
src/Bdd.py
src/ClassIdName.py
src/Config.py
src/Constants.py
src/Extension.py
src/FileName.py
src/FolderImport.py
src/FolderName.py
src/Metadata.py
src/PathName.py
src/Resource.py
src/Type.py
src/Utilities.py
src/__init__.py
src/__main__.py
src/flask_app/__init__.py
src/flask_app/app.py
src/flask_app/static/__init__.py
src/flask_app/templates/__init__.py
archiverr-0.0.12.dist-info/LICENSE
archiverr-0.0.12.dist-info/METADATA
archiverr-0.0.12.dist-info/WHEEL
archiverr-0.0.12.dist-info/top_level.txt
archiverr-0.0.12.dist-info/RECORD
