Metadata-Version: 2.1
Name: archiverr
Version: 0.0.12
Summary: Archiver is a tool to archive, search and extract files and folders based on his sha1
Home-page: https://github.com/theohrlmnn/archiver
Author: Théo Hurlimann
Author-email: theo.hrlmn@eduge.ch
Classifier: Programming Language :: Python :: 3
Classifier: License :: OSI Approved :: BSD License
Classifier: Operating System :: POSIX :: Linux
Requires-Python: >=3.10
License-File: LICENSE
Requires-Dist: setuptools (>=62)
Requires-Dist: Flask (>=2.1.1)
Requires-Dist: numpy (>=1.22.3)
Requires-Dist: pandas (>=1.4.2)
Requires-Dist: py7zr (>=0.17.4)
Requires-Dist: toml (>=0.10.0)
Requires-Dist: orjson (>=3.6.7)
Requires-Dist: python-magic (>=0.4.26)
Requires-Dist: progress (>=1.6)
